LICENSE.BAYKIT
README.md
setup.py
bayserver_docker_ajp/__init__.py
bayserver_docker_ajp/ajp_command.py
bayserver_docker_ajp/ajp_command_handler.py
bayserver_docker_ajp/ajp_command_unpacker.py
bayserver_docker_ajp/ajp_docker.py
bayserver_docker_ajp/ajp_handler.py
bayserver_docker_ajp/ajp_inbound_handler.py
bayserver_docker_ajp/ajp_packet.py
bayserver_docker_ajp/ajp_packet_factory.py
bayserver_docker_ajp/ajp_packet_unpacker.py
bayserver_docker_ajp/ajp_port_docker.py
bayserver_docker_ajp/ajp_protocol_handler.py
bayserver_docker_ajp/ajp_type.py
bayserver_docker_ajp/ajp_warp_docker.py
bayserver_docker_ajp/ajp_warp_handler.py
bayserver_docker_ajp.egg-info/PKG-INFO
bayserver_docker_ajp.egg-info/SOURCES.txt
bayserver_docker_ajp.egg-info/dependency_links.txt
bayserver_docker_ajp.egg-info/requires.txt
bayserver_docker_ajp.egg-info/top_level.txt
bayserver_docker_ajp/command/__init__.py
bayserver_docker_ajp/command/cmd_data.py
bayserver_docker_ajp/command/cmd_end_response.py
bayserver_docker_ajp/command/cmd_forward_request.py
bayserver_docker_ajp/command/cmd_get_body_chunk.py
bayserver_docker_ajp/command/cmd_send_body_chunk.py
bayserver_docker_ajp/command/cmd_send_headers.py
bayserver_docker_ajp/command/cmd_shutdown.py